carbonintensity/__init__.py
carbonintensity/client.py
carbonintensityforked-0.0.3.dist-info/LICENSE
carbonintensityforked-0.0.3.dist-info/METADATA
carbonintensityforked-0.0.3.dist-info/WHEEL
carbonintensityforked-0.0.3.dist-info/top_level.txt
carbonintensityforked-0.0.3.dist-info/RECORD
