Metadata-Version: 2.1
Name: carbonintensityforked
Version: 0.0.3
Summary: Home Assistant Client library for Carbon Intensity API - Adds work by jfparis and alanmcgore to expose additional forecasts and percentage renewables
Home-page: https://github.com/alanmcgore/carbonintensity
Author: Original work by Jorge Cruz-Lambert with additions by Jean-François Paris & Alan Gore
Author-email: alanmcgore@gmail.com
Classifier: Programming Language :: Python :: 3
Classifier: License :: OSI Approved :: MIT License
Classifier: Operating System :: OS Independent
License-File: LICENSE
Requires-Dist: aiohttp
Requires-Dist: numpy
Provides-Extra: test
Requires-Dist: pytest ; extra == 'test'
Requires-Dist: pytest-asyncio ; extra == 'test'
Requires-Dist: aiohttp ; extra == 'test'
Requires-Dist: numpy ; extra == 'test'
